centaur/__init__.py
centaur/version.py
centaur/common/__init__.py
centaur/common/constants.py
centaur/common/error.py
centaur/common/handler.py
centaur/common/logging.py
centaur/common/status.py
centaur/common/types.py
centaur/core/__init__.py
centaur/core/client.py
centaur/core/collection.py
centaur/core/doc.py
centaur/core/partition.py
centaur/core/handler/__init__.py
centaur/core/handler/grpc_handler.py
centaur/core/handler/http_handler.py
centaur/core/models/__init__.py
centaur/core/models/create_collection_request.py
centaur/core/models/create_partition_request.py
centaur/core/models/delete_doc_request.py
centaur/core/models/describe_collection_request.py
centaur/core/models/drop_collection_request.py
centaur/core/models/drop_partition_request.py
centaur/core/models/get_doc_request.py
centaur/core/models/get_version_request.py
centaur/core/models/list_collection_request.py
centaur/core/models/query_doc_request.py
centaur/core/models/stats_collection_request.py
centaur/core/models/upsert_doc_request.py
centaur/core/proto/__init__.py
centaur/core/proto/centaur_pb2.py
centaur/core/proto/centaur_pb2_grpc.py
centaur_client-0.0.11.dist-info/LICENSE.txt
centaur_client-0.0.11.dist-info/METADATA
centaur_client-0.0.11.dist-info/WHEEL
centaur_client-0.0.11.dist-info/top_level.txt
centaur_client-0.0.11.dist-info/RECORD
