Metadata-Version: 2.1
Name: centaur-client
Version: 0.0.11
Summary: Centaur Client Python Sdk Library
Home-page: https://github.com/alibaba/proxima
Author: Alibaba
Author-email: centaur@alibaba-inc.com
License: Apache 2.0
Platform: Posix; MacOS X; Windows
Classifier: Development Status :: 4 - Beta
Classifier: Intended Audience :: Developers
Classifier: License :: OSI Approved :: Apache Software License
Classifier: Programming Language :: Python
Classifier: Programming Language :: Python :: 3
Classifier: Programming Language :: Python :: 3.7
Classifier: Programming Language :: Python :: 3.8
Classifier: Programming Language :: Python :: 3.9
Classifier: Programming Language :: Python :: 3.10
Classifier: Programming Language :: Python :: 3.11
Requires-Python: >=3.7.0
License-File: LICENSE.txt
Requires-Dist: numpy
Requires-Dist: grpcio (>=1.22.0)
Requires-Dist: protobuf (<4.0.0,>=3.8.0)
Requires-Dist: aiohttp (>=3.1.0)
